chunksilo/__init__.py
chunksilo/__main__.py
chunksilo/cfgload.py
chunksilo/cli.py
chunksilo/confluence_html_formatter.py
chunksilo/index.py
chunksilo/search.py
chunksilo/server.py
chunksilo-2.0.0.dist-info/licenses/LICENSE
chunksilo-2.0.0.dist-info/licenses/NOTICE
chunksilo-2.0.0.dist-info/METADATA
chunksilo-2.0.0.dist-info/WHEEL
chunksilo-2.0.0.dist-info/entry_points.txt
chunksilo-2.0.0.dist-info/top_level.txt
chunksilo-2.0.0.dist-info/RECORD
