Metadata-Version: 2.4
Name: chunksilo
Version: 2.0.0
Summary: Local RAG-based semantic document search with MCP server interface
Author: Fredrik Reveny
License-Expression: Apache-2.0
Project-URL: Repository, https://github.com/Chetic/chunksilo
Project-URL: Issues, https://github.com/Chetic/chunksilo/issues
Keywords: rag,mcp,semantic-search,document-search,llm
Classifier: Development Status :: 4 - Beta
Classifier: Programming Language :: Python :: 3
Classifier: Programming Language :: Python :: 3.11
Classifier: Programming Language :: Python :: 3.12
Classifier: Programming Language :: Python :: 3.13
Classifier: Topic :: Text Processing :: Indexing
Classifier: Topic :: Scientific/Engineering :: Artificial Intelligence
Requires-Python: >=3.11
License-File: LICENSE
License-File: NOTICE
Requires-Dist: llama-index<1,>=0.10.0
Requires-Dist: llama-index-readers-file<1,>=0.1.0
Requires-Dist: llama-index-embeddings-fastembed<1,>=0.5.0
Requires-Dist: llama-index-retrievers-bm25<1,>=0.1.0
Requires-Dist: pillow<11,>=10.3.0
Requires-Dist: pypdf<7,>=5.1.0
Requires-Dist: python-docx<2,>=1.1.0
Requires-Dist: mcp<2,>=1.0.0
Requires-Dist: python-dotenv<2,>=1.0.0
Requires-Dist: huggingface-hub<2,>=0.22.0
Requires-Dist: flashrank<1,>=0.1.0
Requires-Dist: fastembed<1,>=0.5.0
Requires-Dist: pyyaml<7,>=6.0
Provides-Extra: confluence
Requires-Dist: llama-index-readers-confluence<1,>=0.6.0; extra == "confluence"
Provides-Extra: test
Requires-Dist: pytest<9,>=7.4.0; extra == "test"
Requires-Dist: requests<3,>=2.31.0; extra == "test"
Dynamic: license-file
